ansys/additive/widgets/__init__.py
ansys/additive/widgets/display/__init__.py
ansys/additive/widgets/display/_common_controls.py
ansys/additive/widgets/display/ave_grain_size_plot.py
ansys/additive/widgets/display/porosity_contour_plot.py
ansys/additive/widgets/display/porosity_eval_plot.py
ansys/additive/widgets/display/show_table.py
ansys/additive/widgets/display/single_bead_eval_plot.py
ansys_additive_widgets-0.2.2.dist-info/licenses/LICENSE
ansys_additive_widgets-0.2.2.dist-info/WHEEL
ansys_additive_widgets-0.2.2.dist-info/METADATA
ansys_additive_widgets-0.2.2.dist-info/RECORD
