Metadata-Version: 2.4
Name: ansys-additive-widgets
Version: 0.2.2
Summary: Visualization toolkit for parametric additive simulations 
Author-email: "ANSYS, Inc." <pyansys.core@ansys.com>
Maintainer-email: "ANSYS, Inc." <pyansys.core@ansys.com>
Requires-Python: >=3.9,<4
License-Expression: MIT
Classifier: Development Status :: 4 - Beta
Classifier: Programming Language :: Python :: 3
Classifier: Operating System :: OS Independent
License-File: LICENSE
Requires-Dist: importlib-metadata >=4.0
Requires-Dist: ansys-additive-core >=0.19, <0.21
Requires-Dist: panel==1.4.4
Requires-Dist: ansys-sphinx-theme[autoapi]==1.3.3 ; extra == "doc"
Requires-Dist: enum-tools==0.12.0 ; extra == "doc"
Requires-Dist: jupyter_sphinx==0.5.3 ; extra == "doc"
Requires-Dist: matplotlib==3.10.1 ; extra == "doc"
Requires-Dist: numpydoc==1.8.0 ; extra == "doc"
Requires-Dist: phantomjs==1.4.1 ; extra == "doc"
Requires-Dist: pypandoc==1.15 ; extra == "doc"
Requires-Dist: pyvista==0.44.2 ; extra == "doc"
Requires-Dist: selenium==4.31.0 ; extra == "doc"
Requires-Dist: sphinx==8.2.3 ; extra == "doc"
Requires-Dist: sphinx-autodoc-typehints==3.1.0 ; extra == "doc"
Requires-Dist: sphinx-copybutton==0.5.2 ; extra == "doc"
Requires-Dist: sphinx-gallery==0.19.0 ; extra == "doc"
Requires-Dist: sphinx-notfound-page==1.1.0 ; extra == "doc"
Requires-Dist: sphinx-toolbox==3.9.0 ; extra == "doc"
Requires-Dist: sphinxemoji==0.3.1 ; extra == "doc"
Requires-Dist: plotly==5.22.0 ; extra == "doc"
Requires-Dist: pytest==8.3.5 ; extra == "tests"
Requires-Dist: pytest-cov==6.1.1 ; extra == "tests"
Requires-Dist: panel==1.4.4 ; extra == "tests"
Project-URL: Documentation, https://widgets.additive.docs.pyansys.com
Project-URL: Homepage, https://github.com/ansys/pyadditive-widgets
Project-URL: Source, https://github.com/ansys/pyadditive-widgets
Project-URL: Tracker, https://github.com/ansys/pyadditive-widgets/issues
Provides-Extra: doc
Provides-Extra: tests
